main.py
mimir/__init__.py
mimir/__version__.py
mimir/config.py
mimir/utils/__init__.py
mimir/utils/chart.py
mimir/utils/common.py
mimir/utils/create_qna.py
mimir/utils/eval.py
mimir/utils/parser.py
mimir_ai-0.0.3.dist-info/METADATA
mimir_ai-0.0.3.dist-info/WHEEL
mimir_ai-0.0.3.dist-info/entry_points.txt
mimir_ai-0.0.3.dist-info/top_level.txt
mimir_ai-0.0.3.dist-info/RECORD
