Metadata-Version: 2.1
Name: mimir-ai
Version: 0.0.3
Requires-Dist: aiohappyeyeballs==2.4.0
Requires-Dist: aiohttp==3.10.5
Requires-Dist: aiosignal==1.3.1
Requires-Dist: annotated-types==0.7.0
Requires-Dist: antlr4-python3-runtime==4.9.3
Requires-Dist: anyio==4.5.0
Requires-Dist: appdirs==1.4.4
Requires-Dist: attrs==24.2.0
Requires-Dist: backoff==2.2.1
Requires-Dist: beautifulsoup4==4.12.3
Requires-Dist: cachetools==5.5.0
Requires-Dist: certifi==2024.8.30
Requires-Dist: cffi==1.17.1
Requires-Dist: chardet==5.2.0
Requires-Dist: charset-normalizer==3.3.2
Requires-Dist: click==8.1.7
Requires-Dist: coloredlogs==15.0.1
Requires-Dist: contourpy==1.3.0
Requires-Dist: cryptography==43.0.1
Requires-Dist: cycler==0.12.1
Requires-Dist: dataclasses-json==0.6.7
Requires-Dist: datasets==3.0.0
Requires-Dist: deepdiff==8.0.1
Requires-Dist: Deprecated==1.2.14
Requires-Dist: dill==0.3.8
Requires-Dist: distro==1.9.0
Requires-Dist: effdet==0.4.1
Requires-Dist: emoji==2.13.0
Requires-Dist: filelock==3.16.1
Requires-Dist: filetype==1.2.0
Requires-Dist: flatbuffers==24.3.25
Requires-Dist: fonttools==4.53.1
Requires-Dist: frozenlist==1.4.1
Requires-Dist: fsspec==2024.6.1
Requires-Dist: google-api-core==2.20.0
Requires-Dist: google-auth==2.35.0
Requires-Dist: google-cloud-vision==3.7.4
Requires-Dist: googleapis-common-protos==1.65.0
Requires-Dist: grpcio==1.66.1
Requires-Dist: grpcio-status==1.66.1
Requires-Dist: h11==0.14.0
Requires-Dist: httpcore==1.0.5
Requires-Dist: httpx==0.27.2
Requires-Dist: huggingface-hub==0.25.0
Requires-Dist: humanfriendly==10.0
Requires-Dist: idna==3.10
Requires-Dist: iopath==0.1.10
Requires-Dist: Jinja2==3.1.4
Requires-Dist: jiter==0.5.0
Requires-Dist: joblib==1.4.2
Requires-Dist: jsonpatch==1.33
Requires-Dist: jsonpath-python==1.0.6
Requires-Dist: jsonpointer==3.0.0
Requires-Dist: kiwisolver==1.4.7
Requires-Dist: langchain==0.2.16
Requires-Dist: langchain-community==0.2.17
Requires-Dist: langchain-core==0.2.40
Requires-Dist: langchain-openai==0.1.25
Requires-Dist: langchain-text-splitters==0.2.4
Requires-Dist: langdetect==1.0.9
Requires-Dist: langsmith==0.1.123
Requires-Dist: layoutparser==0.3.4
Requires-Dist: lxml==5.3.0
Requires-Dist: MarkupSafe==2.1.5
Requires-Dist: marshmallow==3.22.0
Requires-Dist: matplotlib==3.9.2
Requires-Dist: mpmath==1.3.0
Requires-Dist: multidict==6.1.0
Requires-Dist: multiprocess==0.70.16
Requires-Dist: mypy-extensions==1.0.0
Requires-Dist: nest-asyncio==1.6.0
Requires-Dist: networkx==3.3
Requires-Dist: nltk==3.9.1
Requires-Dist: numpy==1.26.4
Requires-Dist: olefile==0.47
Requires-Dist: omegaconf==2.3.0
Requires-Dist: onnx==1.16.2
Requires-Dist: onnxruntime==1.19.2
Requires-Dist: openai==1.46.1
Requires-Dist: opencv-python==4.10.0.84
Requires-Dist: orderly-set==5.2.2
Requires-Dist: orjson==3.10.7
Requires-Dist: packaging==24.1
Requires-Dist: pandas==2.2.2
Requires-Dist: pdf2image==1.17.0
Requires-Dist: pdfminer.six==20231228
Requires-Dist: pdfplumber==0.11.4
Requires-Dist: pi-heif==0.18.0
Requires-Dist: pikepdf==9.2.1
Requires-Dist: pillow==10.4.0
Requires-Dist: portalocker==2.10.1
Requires-Dist: proto-plus==1.24.0
Requires-Dist: protobuf==5.28.2
Requires-Dist: psutil==6.0.0
Requires-Dist: pyarrow==17.0.0
Requires-Dist: pyasn1==0.6.1
Requires-Dist: pyasn1-modules==0.4.1
Requires-Dist: pycocotools==2.0.8
Requires-Dist: pycparser==2.22
Requires-Dist: pydantic==2.9.2
Requires-Dist: pydantic-core==2.23.4
Requires-Dist: pyparsing==3.1.4
Requires-Dist: pypdf==5.0.0
Requires-Dist: pypdfium2==4.30.0
Requires-Dist: pysbd==0.3.4
Requires-Dist: python-dateutil==2.9.0.post0
Requires-Dist: python-iso639==2024.4.27
Requires-Dist: python-magic==0.4.27
Requires-Dist: python-multipart==0.0.9
Requires-Dist: python-oxmsg==0.0.1
Requires-Dist: pytz==2024.2
Requires-Dist: PyYAML==6.0.2
Requires-Dist: ragas==0.1.20
Requires-Dist: rapidfuzz==3.9.7
Requires-Dist: regex==2024.9.11
Requires-Dist: requests==2.32.3
Requires-Dist: requests-toolbelt==1.0.0
Requires-Dist: rsa==4.9
Requires-Dist: safetensors==0.4.5
Requires-Dist: scipy==1.14.1
Requires-Dist: six==1.16.0
Requires-Dist: sniffio==1.3.1
Requires-Dist: soupsieve==2.6
Requires-Dist: SQLAlchemy==2.0.35
Requires-Dist: sympy==1.13.3
Requires-Dist: tabulate==0.9.0
Requires-Dist: tenacity==8.5.0
Requires-Dist: tiktoken==0.7.0
Requires-Dist: timm==1.0.9
Requires-Dist: tokenizers==0.19.1
Requires-Dist: torch==2.4.1
Requires-Dist: torchvision==0.19.1
Requires-Dist: tqdm==4.66.5
Requires-Dist: transformers==4.44.2
Requires-Dist: typing-inspect==0.9.0
Requires-Dist: typing-extensions==4.12.2
Requires-Dist: tzdata==2024.1
Requires-Dist: unstructured==0.15.12
Requires-Dist: unstructured-client==0.25.9
Requires-Dist: unstructured-inference==0.7.36
Requires-Dist: unstructured.pytesseract==0.3.13
Requires-Dist: urllib3==2.2.3
Requires-Dist: wrapt==1.16.0
Requires-Dist: xxhash==3.5.0
Requires-Dist: yarl==1.11.1
